{
  "m_GameObject": {
    "m_FileID": 0,
    "m_PathID": 0
  },
  "m_Enabled": 1,
  "m_Script": {
    "m_FileID": 0,
    "m_PathID": 903313780245196090
  },
  "m_Name": "scene3_block3007_levelgadgets",
  "bytes": [
    3,
    3,
    5,
    35,
    245,
    142,
    182,
    63,
    235,
    2,
    1,
    19,
    202,
    142,
    182,
    63,
    214,
    3,
    1,
    19,
    205,
    142,
    182,
    63,
    248,
    3,
    1,
    19,
    203,
    142,
    182,
    63,
    131,
    4,
    1,
    19,
    192,
    142,
    182,
    63,
    187,
    6,
    1
  ]
}