{
    "_phaseList": [
        {
            "_time": 0.005000000353902578,
            "_type": 9,
            "_blend": 0,
            "_customData": 0,
            "_offPos": {
                "x": 0.15818795561790467,
                "y": -0.2351759374141693,
                "z": 0.17161056399345399
            },
            "_motionPos": {
                "x": 0.0,
                "y": 0.0,
                "z": 0.0
            },
            "_extraTrajName": [],
            "_extraTrajPos": []
        },
        {
            "_time": 0.08400000631809235,
            "_type": 1,
            "_blend": 0,
            "_customData": 0,
            "_offPos": {
                "x": -0.13095277547836305,
                "y": -0.7180085182189941,
                "z": -0.13189753890037538
            },
            "_motionPos": {
                "x": 0.0,
                "y": 0.0,
                "z": 0.0
            },
            "_extraTrajName": [],
            "_extraTrajPos": []
        },
        {
            "_time": 0.12900002300739289,
            "_type": 9,
            "_blend": 0,
            "_customData": 0,
            "_offPos": {
                "x": 0.15303021669387818,
                "y": -0.24222427606582642,
                "z": 0.17508061230182649
            },
            "_motionPos": {
                "x": 0.0,
                "y": 0.0,
                "z": 0.0
            },
            "_extraTrajName": [],
            "_extraTrajPos": []
        },
        {
            "_time": 0.2590000033378601,
            "_type": 9,
            "_blend": 0,
            "_customData": 0,
            "_offPos": {
                "x": 0.1487613320350647,
                "y": -0.2624106705188751,
                "z": 0.1681532859802246
            },
            "_motionPos": {
                "x": 0.0,
                "y": 0.0,
                "z": 0.0
            },
            "_extraTrajName": [],
            "_extraTrajPos": []
        },
        {
            "_time": 0.3889999985694885,
            "_type": 9,
            "_blend": 0,
            "_customData": 0,
            "_offPos": {
                "x": 0.15387791395187379,
                "y": -0.27366623282432558,
                "z": 0.16586115956306458
            },
            "_motionPos": {
                "x": 0.0,
                "y": 0.0,
                "z": 0.0
            },
            "_extraTrajName": [],
            "_extraTrajPos": []
        },
        {
            "_time": 0.5189999938011169,
            "_type": 9,
            "_blend": 0,
            "_customData": 0,
            "_offPos": {
                "x": 0.15780620276927949,
                "y": -0.2593386769294739,
                "z": 0.1742536425590515
            },
            "_motionPos": {
                "x": 0.0,
                "y": 0.0,
                "z": 0.0
            },
            "_extraTrajName": [],
            "_extraTrajPos": []
        },
        {
            "_time": 0.6489999890327454,
            "_type": 9,
            "_blend": 0,
            "_customData": 0,
            "_offPos": {
                "x": 0.15843743085861207,
                "y": -0.2387814223766327,
                "z": 0.18030942976474763
            },
            "_motionPos": {
                "x": 0.0,
                "y": 0.0,
                "z": 0.0
            },
            "_extraTrajName": [],
            "_extraTrajPos": []
        },
        {
            "_time": 0.7789999842643738,
            "_type": 9,
            "_blend": 0,
            "_customData": 0,
            "_offPos": {
                "x": 0.15837137401103974,
                "y": -0.23464953899383546,
                "z": 0.17307765781879426
            },
            "_motionPos": {
                "x": 0.0,
                "y": 0.0,
                "z": 0.0
            },
            "_extraTrajName": [],
            "_extraTrajPos": []
        }
    ],
    "_zoneList": [
        {
            "_timeSpan": {
                "x": -0.0009999724570661784,
                "y": 0.8333333134651184
            },
            "_name": "SlipFaceWall",
            "_nameHash": 0,
            "_beginMotionPos": {
                "x": 0.0,
                "y": 0.0,
                "z": 0.0
            },
            "_endMotionPos": {
                "x": 0.0,
                "y": 0.0,
                "z": 0.0
            }
        }
    ]
}