{
  "m_GameObject": {
    "m_FileID": 0,
    "m_PathID": 0
  },
  "m_Enabled": 1,
  "m_Script": {
    "m_FileID": 0,
    "m_PathID": 903313780245196090
  },
  "m_Name": "scene50004_block50004_levelmonsters",
  "bytes": [
    3,
    212,
    134,
    3,
    4,
    51,
    164,
    132,
    155,
    119,
    1,
    15,
    68,
    101,
    102,
    97,
    117,
    108,
    116,
    84,
    101,
    109,
    112,
    108,
    97,
    116,
    101,
    1,
    51,
    167,
    132,
    155,
    119,
    2,
    15,
    68,
    101,
    102,
    97,
    117,
    108,
    116,
    84,
    101,
    109,
    112,
    108,
    97,
    116,
    101,
    1,
    51,
    167,
    132,
    155,
    119,
    3,
    15,
    68,
    101,
    102,
    97,
    117,
    108,
    116,
    84,
    101,
    109,
    112,
    108,
    97,
    116,
    101,
    1,
    51,
    167,
    132,
    155,
    119,
    4,
    15,
    68,
    101,
    102,
    97,
    117,
    108,
    116,
    84,
    101,
    109,
    112,
    108,
    97,
    116,
    101,
    1
  ]
}